nichtparasoup/__init__.py
nichtparasoup/__main__.py
nichtparasoup/__version__.py
nichtparasoup/py.typed
nichtparasoup/_internals/__init__.py
nichtparasoup/cli/__init__.py
nichtparasoup/cli/commands.py
nichtparasoup/cli/main.py
nichtparasoup/cli/parser.py
nichtparasoup/config/__init__.py
nichtparasoup/config/defaults.yaml
nichtparasoup/config/schema.yaml
nichtparasoup/core/__init__.py
nichtparasoup/core/image.py
nichtparasoup/core/imagecrawler.py
nichtparasoup/core/server.py
nichtparasoup/imagecrawler/__init__.py
nichtparasoup/imagecrawler/echo.py
nichtparasoup/imagecrawler/instagram.py
nichtparasoup/imagecrawler/picsum.py
nichtparasoup/imagecrawler/pr0gramm.py
nichtparasoup/imagecrawler/reddit.py
nichtparasoup/testing/__init__.py
nichtparasoup/testing/config.py
nichtparasoup/testing/imagecrawler.py
nichtparasoup/webserver/__init__.py
nichtparasoup/webserver/htdocs/static/_features.html
nichtparasoup/webserver/htdocs/static/index.html
nichtparasoup/webserver/htdocs/static/css/feel.css
nichtparasoup/webserver/htdocs/static/css/look.css
nichtparasoup/webserver/htdocs/static/css/look_bossMode.css
nichtparasoup/webserver/htdocs/static/css/look_buttons.css
nichtparasoup/webserver/htdocs/static/css/look_fullscreen.css
nichtparasoup/webserver/htdocs/static/css/look_hotkeys.css
nichtparasoup/webserver/htdocs/static/css/look_stateSwitch.css
nichtparasoup/webserver/htdocs/static/css/normalize.css
nichtparasoup/webserver/htdocs/static/js/feel.js
nichtparasoup/webserver/htdocs/static/js/feel_hotkeys.js
nichtparasoup/webserver/htdocs/static/js/helper.js
nichtparasoup/webserver/htdocs/static/js/look_maxSizer.js
nichtparasoup/webserver/htdocs/static/js/look_stateSwitch.js
nichtparasoup/webserver/htdocs/template/css/sourceIcons.css
nichtparasoup-2.5.1.dist-info/AUTHORS
nichtparasoup-2.5.1.dist-info/LICENSE
nichtparasoup-2.5.1.dist-info/METADATA
nichtparasoup-2.5.1.dist-info/WHEEL
nichtparasoup-2.5.1.dist-info/entry_points.txt
nichtparasoup-2.5.1.dist-info/top_level.txt
nichtparasoup-2.5.1.dist-info/RECORD
