Metadata-Version: 2.1
Name: nichtparasoup
Version: 2.5.1
Summary: A hackspaces entertainment system
Home-page: https://github.com/k4cg/nichtparasoup/
Author: K4CG
Author-email: info@k4cg.org
License: MIT
Project-URL: Source, https://github.com/k4cg/nichtparasoup/
Project-URL: Documentation, https://github.com/k4cg/nichtparasoup/tree/master/docs
Keywords: image-crawler,instagram,pr0gramm,reddit
Platform: UNKNOWN
Classifier: Development Status :: 5 - Production/Stable
Classifier: Environment :: Web Environment
Classifier: License :: OSI Approved :: MIT License
Classifier: Operating System :: OS Independent
Classifier: Programming Language :: Python
Classifier: Programming Language :: Python :: 3 :: Only
Classifier: Programming Language :: Python :: 3.5
Classifier: Programming Language :: Python :: 3.6
Classifier: Programming Language :: Python :: 3.7
Classifier: Programming Language :: Python :: 3.8
Classifier: Topic :: Games/Entertainment
Classifier: Topic :: Internet :: WWW/HTTP :: Dynamic Content
Classifier: Typing :: Typed
Requires-Python: >=3.5
Requires-Dist: ruamel.yaml (>=0.16)
Requires-Dist: yamale (>=2.0)
Requires-Dist: werkzeug (<2.0,>=1.0)
Requires-Dist: mako (>=1.1)
Requires-Dist: setuptools (>=40.0)
Requires-Dist: argcomplete (>=1.11)
Requires-Dist: typing-extensions (>=3.7.4) ; python_version < "3.8"
Provides-Extra: colors
Requires-Dist: termcolor (>=1.1) ; extra == 'colors'
Provides-Extra: development
Requires-Dist: tox (>=3.14) ; extra == 'development'
Requires-Dist: isort (>=4.3) ; extra == 'development'
Requires-Dist: autopep8 (>=1.5) ; extra == 'development'
Provides-Extra: testing
Requires-Dist: flake8 (>=3.7) ; extra == 'testing'
Requires-Dist: flake8-isort (>=2.8) ; extra == 'testing'
Requires-Dist: flake8-pep3101 (>=1.3) ; extra == 'testing'
Requires-Dist: pep8-naming (>=0.9) ; extra == 'testing'
Requires-Dist: mypy (>=0.761) ; extra == 'testing'
Requires-Dist: coverage (>=5.0) ; extra == 'testing'
Requires-Dist: pytest (>=5.3) ; extra == 'testing'
Requires-Dist: ddt (>=1.2) ; extra == 'testing'
Requires-Dist: flake8-bugbear (>=19.8) ; (python_version < "3.6") and extra == 'testing'
Requires-Dist: flake8-annotations (>=2.0) ; (python_version >= "3.6") and extra == 'testing'
Requires-Dist: flake8-bugbear (>=20.1) ; (python_version >= "3.6") and extra == 'testing'
